TradeGate.py
Exchanges/BaseExchange.py
Exchanges/BinanceExchange.py
Exchanges/BybitExchange.py
Exchanges/KuCoinExchange.py
Exchanges/__init__.py
Utils/BinanceHelpers.py
Utils/BybitHelpers.py
Utils/DataHelpers.py
Utils/KuCoinHelpers.py
Utils/__init__.py
Watchers/__init__.py
Watchers/futureOrderWatchers.py
binance_f/__init__.py
binance_f/requestclient.py
binance_f/subscriptionclient.py
binance_f/base/__init__.py
binance_f/base/printobject.py
binance_f/base/printtime.py
binance_f/constant/__init__.py
binance_f/constant/system.py
binance_f/constant/test.py
binance_f/exception/__init__.py
binance_f/exception/binanceapiexception.py
binance_f/impl/__init__.py
binance_f/impl/restapiinvoker.py
binance_f/impl/restapirequest.py
binance_f/impl/restapirequestimpl.py
binance_f/impl/websocketconnection.py
binance_f/impl/websocketrequest.py
binance_f/impl/websocketrequestimpl.py
binance_f/impl/websocketwatchdog.py
binance_f/impl/utils/__init__.py
binance_f/impl/utils/apisignature.py
binance_f/impl/utils/channelparser.py
binance_f/impl/utils/channels.py
binance_f/impl/utils/inputchecker.py
binance_f/impl/utils/jsonwrapper.py
binance_f/impl/utils/timeservice.py
binance_f/impl/utils/urlparamsbuilder.py
binance_f/model/__init__.py
binance_f/model/accountinformation.py
binance_f/model/accountinformationv2.py
binance_f/model/accountupdate.py
binance_f/model/adlquantile.py
binance_f/model/aggregatetrade.py
binance_f/model/aggregatetradeevent.py
binance_f/model/apitradingstatus.py
binance_f/model/balance.py
binance_f/model/balancev2.py
binance_f/model/blvtinfoevent.py
binance_f/model/blvtnavcandlestick.py
binance_f/model/blvtnavcandlestickevent.py
binance_f/model/candlestick.py
binance_f/model/candlestickevent.py
binance_f/model/codeandmsg.py
binance_f/model/compositeindexevent.py
binance_f/model/constant.py
binance_f/model/continuouscandelstickevent.py
binance_f/model/countdowncancelall.py
binance_f/model/diffdepthevent.py
binance_f/model/exchangeinformation.py
TradeGates-0.3.9.dist-info/LICENSE
TradeGates-0.3.9.dist-info/METADATA
TradeGates-0.3.9.dist-info/WHEEL
TradeGates-0.3.9.dist-info/top_level.txt
TradeGates-0.3.9.dist-info/RECORD
