Metadata-Version: 2.1
Name: TradeGates
Version: 0.3.9
Summary: A Trading Gateway
Author: Rustin Soraki
Author-email: Rustin Soraki <rustin.soraki@gmail.com>
Classifier: Programming Language :: Python :: 3
Classifier: License :: OSI Approved :: MIT License
Classifier: Operating System :: OS Independent
Requires-Python: >=3.6
License-File: LICENSE
Requires-Dist: binance-connector
Requires-Dist: requests
Requires-Dist: apscheduler
Requires-Dist: websocket-client
Requires-Dist: urllib3
Requires-Dist: tzlocal <3.0
Requires-Dist: pandas
Requires-Dist: pybit
